{
 "model": "mythomax-l2-13b",
 "slug": "gryphe/mythomax-l2-13b",
 "tag": {
  "cat": {
   "x": [
    " Yes.",
    " Yes.",
    " Yes.",
    " Yes."
   ],
   "y": [
    " Yes.",
    " Yes.",
    " Yes.",
    " Yes."
   ]
  },
  "puppy": {
   "x": [
    " Yes.",
    " Yes.",
    " Yes.",
    " Yes."
   ],
   "y": [
    " Yes.",
    " No.",
    " Yes.",
    " Yes."
   ]
  },
  "boat": {
   "x": [
    " Yes.",
    " Yes.",
    " Yes, Serenity is a great name for a sailboat.",
    " Yes."
   ],
   "y": [
    " Yes.",
    " Yes.",
    " Yes.",
    " Yes."
   ]
  },
  "chore": {
   "x": [
    " Yes.",
    " Yes.",
    " Yes",
    " Yes."
   ],
   "y": [
    " Yes",
    " Yes.",
    " Yes.",
    " Yes."
   ]
  },
  "workout": {
   "x": [
    " Yes.",
    " Yes.",
    " Yes.",
    " Yes"
   ],
   "y": [
    " Yes.",
    " Yes",
    " Yes",
    " Yes."
   ]
  },
  "drink": {
   "x": [
    " Yes.",
    " Yes.",
    " Yes.",
    " Yes."
   ],
   "y": [
    " Yes.",
    " Yes.",
    " Yes.",
    " Yes."
   ]
  },
  "dinner": {
   "x": [
    " Yes.",
    " Yes.",
    " Yes.",
    " Yes."
   ],
   "y": [
    " Yes.",
    " Yes.",
    " Yes.",
    " Yes"
   ]
  },
  "wall": {
   "x": [
    " Yes.",
    " Yes.",
    " Yes",
    " No."
   ],
   "y": [
    " Yes.",
    " Yes.",
    " Yes.",
    " Yes."
   ]
  },
  "pet": {
   "x": [
    " Yes.",
    " Yes.",
    " Yes.",
    " Yes."
   ],
   "y": [
    " Yes.",
    " Yes.",
    " Yes.",
    " Yes."
   ]
  },
  "vacation": {
   "x": [
    " Yes.",
    " Yes.",
    " Yes.",
    " Yes."
   ],
   "y": [
    " Yes",
    " Yes.",
    " Yes.",
    " Yes."
   ]
  },
  "language": {
   "x": [
    " Yes.",
    " Yes.",
    " Yes.",
    " Yes. Python is a popular and widely used programming language with a simple syntax that is easy to learn. It has numerous applications in data science, machine learning, web development, and more."
   ],
   "y": [
    " Yes.",
    " No, it depends on your goals and interests.",
    " Yes",
    " Yes."
   ]
  },
  "phone": {
   "x": [
    " Yes.",
    " Yes.",
    " Yes.",
    " No."
   ],
   "y": [
    " Yes.",
    " Yes.",
    " Yes.",
    " Yes."
   ]
  },
  "bonus": {
   "x": [
    " Yes.",
    " Yes.",
    " Yes.",
    " Yes."
   ],
   "y": [
    " Yes.",
    " Yes.",
    " Yes.",
    " Yes."
   ]
  },
  "job": {
   "x": [
    " No.",
    " Yes.",
    " Yes.",
    " Yes."
   ],
   "y": [
    " Yes.",
    " There is no one-size-fits-all answer to this question as it depends on your personal preferences, career goals, and the specific details of both the job offers. Consider factors such as job stability, growth opportunities, company culture, and compensation when making your decision. Both a startup and a corporation can offer unique advantages and challenges.",
    " Yes.",
    " Yes."
   ]
  },
  "home": {
   "x": [
    " Yes.",
    " It depends on several factors such as your financial situation, location, and future plans.",
    " Yes, buying a home is generally considered a better choice from a long-term financial perspective.",
    " Not necessarily. Buying a house comes with higher upfront costs, ongoing maintenance expenses, and potential financial risks. Renting can provide flexibility, lower initial costs, and less responsibility for repairs and maintenance. Ultimately, the decision depends on your individual circumstances, future plans, and preferences."
   ],
   "y": [
    " Yes.",
    " Yes.",
    " No, it depends on your individual circumstances and preferences. Both renting and buying have their advantages and disadvantages.",
    " There is not enough information provided to give a clear answer. Renting can be a better choice for flexibility, lower upfront costs, and not being responsible for maintenance and repairs. However, it also means giving up control over property and potentially facing rent increases or uncertainty around lease renewals. Homeownership can provide stability, equity, and the ability to customize your living space. Ultimately, the decision depends on individual circumstances like income, family size, location, and long-term goals."
   ]
  },
  "school": {
   "x": [
    " It depends on your career goals and what you want to study. A master's degree can provide specialized knowledge and skills, which may be necessary for certain jobs or industries. However, it also requires additional time and money. You should consider your long-term plans, research potential career paths, and weigh the costs and benefits before making a decision.",
    " Yes.",
    " Yes.",
    " Yes."
   ],
   "y": [
    " Yes.",
    " Yes.",
    " Yes, working for a few years before deciding on the next step can provide valuable experience and help clarify your career goals.",
    " Yes."
   ]
  },
  "move": {
   "x": [
    " Yes.",
    " Yes.",
    " Yes.",
    " Yes."
   ],
   "y": [
    " No.",
    " No relocation process is a major life change. It can be beneficial to assess the pros and cons of staying or relocating before making a final decision. You could also consider talking to friends, family, or professionals to help weigh your options.",
    " Yes.",
    " No."
   ]
  },
  "car": {
   "x": [
    " Yes.",
    " Yes",
    " Yes.",
    " Yes."
   ],
   "y": [
    " Yes.",
    " Yes.",
    " Yes.",
    " Yes."
   ]
  },
  "major": {
   "x": [
    " Yes.",
    " Yes.",
    " Yes.",
    " Yes."
   ],
   "y": [
    " Yes.",
    " Yes.",
    " No.",
    " Yes"
   ]
  },
  "commute": {
   "x": [
    " Yes.",
    " Yes",
    " Yes.",
    " Yes."
   ],
   "y": [
    " No.",
    " Yes.",
    " It depends on a variety of factors such as distance, traffic, parking, and personal preferences. If the commute is long and there is heavy traffic, public transportation or carpooling may be a better option. However, if the distance is short and parking is easily accessible, driving may be the most convenient choice. Ultimately, it is up to the individual to consider all factors and make the decision that best suits their needs.",
    " No."
   ]
  }
 }
}